whiteboard/__init__.py
whiteboard/colors.py
whiteboard/getsys.py
whiteboard/interface.py
whiteboard/list.py
whiteboard/main.py
whiteboard_bin-0.0.1.dist-info/LICENSE
whiteboard_bin-0.0.1.dist-info/METADATA
whiteboard_bin-0.0.1.dist-info/WHEEL
whiteboard_bin-0.0.1.dist-info/top_level.txt
whiteboard_bin-0.0.1.dist-info/RECORD
