Metadata-Version: 2.1
Name: whiteboard-bin
Version: 0.0.1
Summary: A lightweight package information utility. 
Home-page: https://github.com/howardjs/whiteboard
Author: Garrett Howard
Author-email: garrett@mersh.com
License: MIT License
